pymdownlz/__init__.py
pymdownlz/inline.py
pymd_extensions_lz-0.0.1.dist-info/LICENSE.md
pymd_extensions_lz-0.0.1.dist-info/METADATA
pymd_extensions_lz-0.0.1.dist-info/WHEEL
pymd_extensions_lz-0.0.1.dist-info/top_level.txt
pymd_extensions_lz-0.0.1.dist-info/RECORD
